diyr/__init__.py
diyr/args.py
diyr/command_line.py
diyr/main.py
diyr/engines/__init__.py
diyr/engines/base.py
diyr/engines/fitb.py
diyr/example_format_types/listed_verses.txt
diyr/formattypes/__init__.py
diyr/formattypes/base.py
diyr/formattypes/listed_verses.py
diyr/formattypes/outline.py
diyr/formattypes/referenced_verses.py
diyr/sinks/__init__.py
diyr/sinks/base.py
diyr/sinks/nothing.py
diyr/sinks/seek.py
diyr/sinks/shuffle.py
diyr/sources/__init__.py
diyr/sources/base.py
diyr/sources/file.py
diyr/sources/online.py
diyr/utils/__init__.py
diyr/utils/bible.py
diyr/utils/test_utils.py
diyr-0.0.1a17.dist-info/DESCRIPTION.rst
diyr-0.0.1a17.dist-info/METADATA
diyr-0.0.1a17.dist-info/RECORD
diyr-0.0.1a17.dist-info/WHEEL
diyr-0.0.1a17.dist-info/entry_points.txt
diyr-0.0.1a17.dist-info/metadata.json
diyr-0.0.1a17.dist-info/top_level.txt
