Metadata-Version: 2.0
Name: diyr
Version: 0.0.1a17
Summary: An interactive program that hollows out text fileswith verses, references, and ministry excerpts.
Home-page: https://github.com/alextricity25/dwell_in_you_richly
Author: Miguel Alex Cantu
Author-email: miguel.can2@gmail.com	
License: GNU General Public License v3 or later (GPLv3+)
Download-URL: https://github.com/alextricity25/dwell_in_you_richly/archive/0.0.1a17.tar.gz
Keywords: Study Bible,Memorize Bible
Platform: UNKNOWN
Requires-Dist: pyparsing
Requires-Dist: beautifulsoup4
Requires-Dist: requests
